slack_message/__init__.py
slack_message/blocks/__init__.py
slack_message/blocks/actions.c
slack_message/blocks/actions.cp312-win_amd64.pyd
slack_message/blocks/context.c
slack_message/blocks/context.cp312-win_amd64.pyd
slack_message/blocks/divider.c
slack_message/blocks/divider.cp312-win_amd64.pyd
slack_message/blocks/header.c
slack_message/blocks/header.cp312-win_amd64.pyd
slack_message/blocks/image.c
slack_message/blocks/image.cp312-win_amd64.pyd
slack_message/blocks/input.c
slack_message/blocks/input.cp312-win_amd64.pyd
slack_message/blocks/rich_text.c
slack_message/blocks/rich_text.cp312-win_amd64.pyd
slack_message/blocks/section.c
slack_message/blocks/section.cp312-win_amd64.pyd
slack_message/blocks/table.c
slack_message/blocks/table.cp312-win_amd64.pyd
slack_message/bot/__init__.py
slack_message/config/__init__.py
slack_message/file_management/__init__.py
slack_message/interface/__init__.py
slack_message/messages/__init__.py
slack_message/messages/actions/__init__.py
slack_message/messages/actions/datepickers.c
slack_message/messages/actions/datepickers.cp312-win_amd64.pyd
slack_message/messages/composite/__init__.py
slack_message/messages/composite/button.c
slack_message/messages/composite/button.cp312-win_amd64.pyd
slack_message/messages/composite/checkboxes.c
slack_message/messages/composite/checkboxes.cp312-win_amd64.pyd
slack_message/messages/composite/dataframe.c
slack_message/messages/composite/dataframe.cp312-win_amd64.pyd
slack_message/messages/composite/radio_buttons.c
slack_message/messages/composite/radio_buttons.cp312-win_amd64.pyd
slack_message/messages/composite/time_picker.c
slack_message/messages/composite/time_picker.cp312-win_amd64.pyd
slack_message/messages/context/__init__.py
slack_message/messages/context/context.c
slack_message/messages/context/context.cp312-win_amd64.pyd
slack_message/messages/header/__init__.py
slack_message/messages/header/header.c
slack_message/messages/header/header.cp312-win_amd64.pyd
slack_message-0.0.7.dist-info/METADATA
slack_message-0.0.7.dist-info/WHEEL
slack_message-0.0.7.dist-info/top_level.txt
slack_message-0.0.7.dist-info/RECORD
