Metadata-Version: 2.4
Name: slack-message
Version: 0.0.7
Summary: A flexible and easy-to-use library for creating and sending messages to Slack
Author: Alex
Requires-Python: >=3.12
Requires-Dist: python-dotenv
Requires-Dist: slack-sdk
Requires-Dist: tenacity
Requires-Dist: pandas
Requires-Dist: tabulate
Requires-Dist: pandas
Provides-Extra: dev
Dynamic: requires-python
